README.rst
setup.py
redq/__init__.py
redq/redq.py
redq.egg-info/PKG-INFO
redq.egg-info/SOURCES.txt
redq.egg-info/dependency_links.txt
redq.egg-info/requires.txt
redq.egg-info/top_level.txt
test/test.py
test/test_multi.py