Metadata-Version: 1.1
Name: redq
Version: 1.0.2
Summary: A Redis-based message queue library
Home-page: http://github.com/peterfraedrich/redq
Author: Peter Fraedrich
Author-email: peter.fraedrich@hexapp.net
License: MIT
Keywords: Redis,message,queue,mq,FIFO
Platform: any
Classifier: Development Status :: 4 - Beta
Classifier: Intended Audience :: Developers
Classifier: License :: OSI Approved :: MIT License
Classifier: Operating System :: Microsoft :: Windows
Classifier: Operating System :: MacOS
Classifier: Operating System :: POSIX
Classifier: Programming Language :: Python
Classifier: Topic :: Software Development :: Libraries
Classifier: Topic :: Software Development :: Libraries :: Python Modules
